raknet-0.3.0.dist-info/WHEEL
raknet-0.3.0.dist-info/METADATA
raknet-0.3.0.dist-info/entry_points.txt
raknet-0.3.0.dist-info/RECORD
raknet-0.3.0.dist-info/licenses/LICENSE
raknet/_raknet.cpython-312-x86_64-linux-gnu.so
raknet/__init__.py
raknet/_raknet.pyi
