Metadata-Version: 2.1
Name: raknet
Version: 0.3.0
Summary: Python bindings for the RakNet networking library
Keywords: python raknet network
Author-Email: Vincent Wu <magicdroidx@gmail.com>
License: BSD 3-Clause License
Classifier: Development Status :: 3 - Alpha
Classifier: License :: OSI Approved :: BSD License
Classifier: Operating System :: MacOS
Classifier: Operating System :: Microsoft :: Windows
Classifier: Operating System :: POSIX :: Linux
Classifier: Programming Language :: C++
Classifier: Programming Language :: Python
Classifier: Programming Language :: Python :: 3
Classifier: Programming Language :: Python :: 3.9
Classifier: Programming Language :: Python :: 3.10
Classifier: Programming Language :: Python :: 3.11
Classifier: Programming Language :: Python :: 3.12
Classifier: Topic :: System :: Networking
Project-URL: Documentation, https://raknet-python.readthedocs.io
Project-URL: Homepage, https://github.com/raknet-python/raknet-python
Project-URL: Issues, https://github.com/raknet-python/raknet-python/issues
Requires-Python: >=3.9
License-File: LICENSE
